kamangir/README.py
kamangir/__init__.py
kamangir/__main__.py
kamangir/content.py
kamangir/logger.py
kamangir/urls.py
kamangir/.abcli/actions.sh
kamangir/.abcli/kamangir.sh
kamangir/.abcli/tests/build_README.sh
kamangir/.abcli/tests/help.sh
kamangir/.abcli/tests/version.sh
kamangir/help/__init__.py
kamangir/help/__main__.py
kamangir/help/functions.py
kamangir-3.185.1.dist-info/LICENSE
kamangir-3.185.1.dist-info/METADATA
kamangir-3.185.1.dist-info/WHEEL
kamangir-3.185.1.dist-info/top_level.txt
kamangir-3.185.1.dist-info/RECORD
