Metadata-Version: 2.2
Name: kamangir
Version: 3.185.1
Summary: 📜 github/kamangir.
Home-page: https://github.com/kamangir/kamangir
Author: Arash Abadpour (Kamangir)
Author-email: arash@kamangir.net
License: Public Domain
Classifier: Programming Language :: Python :: 3
Classifier: Programming Language :: Unix Shell
Classifier: License :: Public Domain
Classifier: Operating System :: OS Independent
License-File: LICENSE
Requires-Dist: blueness
Requires-Dist: abcli
Requires-Dist: abadpour
Requires-Dist: blue_plugin
Requires-Dist: blue_geo
Requires-Dist: blueflow
Requires-Dist: blue_stability
Requires-Dist: blue_codespace
Requires-Dist: articraft
Requires-Dist: boto3
Requires-Dist: ferfereh
Requires-Dist: gizai
Requires-Dist: hubblescope
Requires-Dist: numpy
Requires-Dist: openai_commands
Requires-Dist: pymysql
Requires-Dist: pyyaml
Requires-Dist: pylint
Requires-Dist: pytest
Requires-Dist: python-dotenv[cli]
Requires-Dist: roofai
Requires-Dist: tqdm
Requires-Dist: vancouver_watching
Requires-Dist: palisades
Dynamic: author
Dynamic: author-email
Dynamic: classifier
Dynamic: description
Dynamic: description-content-type
Dynamic: home-page
Dynamic: license
Dynamic: requires-dist
Dynamic: summary
